{
	"zhekou_discover_left_nav": [{
			"element_id": 21826,
			"element_type": "webview",
			"title": "热门",
			"subtitle": "0",
			"extend": "",
			"pic": "",
			"pic2": "",
			"pic_width": 0,
			"pic_height": 0,
			"index": 2,
			"is_show_title": 0,
			"show_type": 1,
			"is_ad": 0,
			"tag": "0",
			"position": 0,
			"attach": "",
			"color_num": "0",
			"module_id": 100,
			"offline_time": 2082470400,
			"parent_element": 0,
			"children": {
				"banner": [{
					"element_id": 9744,
					"element_type": "banner",
					"title": "banner",
					"subtitle": "",
					"extend": "http:\/\/m.sqkb.com\/coupon\/23027382\/",
					"pic": "drawable://R.drawable.classify5",
					"pic2": "",
					"pic_width": 900,
					"pic_height": 288,
					"index": 0,
					"is_show_title": 0,
					"show_type": 1,
					"is_ad": 0,
					"tag": "0",
					"position": 0,
					"attach": {
						"channel_id": "222"
					},
					"color_num": "0",
					"module_id": 101,
					"offline_time": 1546704000,
					"parent_element": 9725
				}],
				"webview": [{
						"element_id": 21849,
						"element_type": "webview",
						"title": "搬家",
						"subtitle": "10公里运输及小件行李物品搬运",
						"extend": "http:\/\/m.ibantang.com\/zhekou\/g\/442\/",
						"pic": "http://t07img.yangkeduo.com/images/2018-04-25/97cedd15e01364cd56bfb7d55e9c8e92.png",
						"pic2": "",
						"pic_width": 200,
						"pic_height": 200,
						"index": 6,
						"time": "总价=基础费用+额外需求费用",
						"price": "700",
						"is_show_title": 0,
						"show_type": 1,
						"is_ad": 0,
						"tag": "0",
						"position": 0,
						"attach": "",
						"color_num": "0",
						"module_id": 101,
						"offline_time": 1584028800,
						"parent_element": 21826
					},
					{
						"element_id": 23251,
						"element_type": "webview",
						"title": "上门推拿",
						"subtitle": "上门按摩SPA调理保健",
						"extend": "http:\/\/m.ibantang.com\/zhekou\/g\/496\/",
						"pic": "http://t08img.yangkeduo.com/images/2018-04-19/ef86c99733c4cd53477aea253eee016c.png",
						"pic2": "",
						"time": "1小时起",
				  		"price": "199",
						"pic_width": 200,
						"pic_height": 200,
						"index": 2,
						"is_show_title": 0,
						"show_type": 1,
						"is_ad": 0,
						"tag": "0",
						"position": 0,
						"attach": "",
						"color_num": "0",
						"module_id": 101,
						"offline_time": 1586966400,
						"parent_element": 21826
					},
					{
						"element_id": 21889,
						"element_type": "webview",
						"title": "鲜花",
						"subtitle": "玫瑰鲜花康乃馨鲜花速递",
						"extend": "http:\/\/m.ibantang.com\/zhekou\/g\/410\/",
						"pic": "http://t03img.yangkeduo.com/images/2018-04-19/287418e28ef4eff267d84148c25f8d9c.png",
						"pic2": "",
					  	"time": "同城花店配送鲜花",
				  		"price": "368",
						"pic_width": 200,
						"pic_height": 200,
						"index": 1,
						"is_show_title": 0,
						"show_type": 1,
						"is_ad": 0,
						"tag": "0",
						"position": 0,
						"attach": "",
						"color_num": "0",
						"module_id": 101,
						"offline_time": 1584028800,
						"parent_element": 21826
					},
					{
						"element_id": 21879,
						"element_type": "webview",
						"title": "清洗特惠",
						"subtitle": "清洗羽绒服棉服",
						"extend": "http:\/\/m.ibantang.com\/zhekou\/g\/497\/",
						"pic": "http://t07img.yangkeduo.com/images/2018-04-19/28bb4d672a7f456fb75f1734183e0aa8.png",
						"pic2": "",
						"pic_width": 200,
						"pic_height": 200,
					  	"time": "三件及以上免费上门取送",
				  		"price": "49.9",
						"index": 2,
						"is_show_title": 0,
						"show_type": 1,
						"is_ad": 0,
						"tag": "0",
						"position": 0,
						"attach": "",
						"color_num": "0",
						"module_id": 101,
						"offline_time": 1584028800,
						"parent_element": 21826
					},
					{
						"element_id": 23256,
						"element_type": "webview",
						"title": "洗油烟机",
						"subtitle": "清除油污、高温消毒、预防腐蚀、节省耗电",
						"extend": "http:\/\/m.ibantang.com\/zhekou\/g\/498\/",
						"pic": "http://t07img.yangkeduo.com/images/2018-04-19/a3195d9f6eff8e8a42671349438820f7.png",
						"pic2": "",
						"pic_width": 200,
						"pic_height": 200,
					  	"time": "会员享8.5折",
				  		"price": "180",
						"index": 4,
						"is_show_title": 0,
						"show_type": 1,
						"is_ad": 0,
						"tag": "0",
						"position": 0,
						"attach": "",
						"color_num": "0",
						"module_id": 101,
						"offline_time": 1586966400,
						"parent_element": 21826
					},
					{
						"element_id": 21864,
						"element_type": "webview",
						"title": "修洗衣机",
						"subtitle": "失效保障、明码标价、质保返修",
						"extend": "http:\/\/m.ibantang.com\/zhekou\/g\/409\/",
						"pic": "http://t05img.yangkeduo.com/images/2018-03-05/a84cfd10275709465795c6c17e108199.png",
						"pic2": "",
						"pic_width": 200,
						"pic_height": 200,
					  	"time": "会员享8.5折",
				  		"price": "180",
						"index": 6,
						"is_show_title": 0,
						"show_type": 1,
						"is_ad": 0,
						"tag": "0",
						"position": 0,
						"attach": "",
						"color_num": "0",
						"module_id": 101,
						"offline_time": 1584028800,
						"parent_element": 21826
					}
				]
			}
		},
		{
			"element_id": 21828,
			"element_type": "webview",
			"title": "保洁清洁",
			"subtitle": "0",
			"extend": "",
			"pic": "",
			"pic2": "",
			"pic_width": 0,
			"pic_height": 0,
			"index": 3,
			"is_show_title": 0,
			"show_type": 1,
			"is_ad": 0,
			"tag": "0",
			"position": 0,
			"attach": "",
			"color_num": "0",
			"module_id": 100,
			"offline_time": 1735315200,
			"parent_element": 0,
			"children": {
				"banner": [{
					"element_id": 9744,
					"element_type": "banner",
					"title": "banner",
					"subtitle": "",
					"extend": "http:\/\/m.sqkb.com\/coupon\/23027382\/",
					"pic": "http:\/\/file.17gwx.com\/sqkb\/element\/2018\/03\/12\/402425aa5fa0541daa.jpg",
					"pic2": "",
					"pic_width": 900,
					"pic_height": 288,
					"index": 4,
					"is_show_title": 0,
					"show_type": 1,
					"is_ad": 0,
					"tag": "0",
					"position": 0,
					"attach": {
						"channel_id": "222"
					},
					"color_num": "0",
					"module_id": 101,
					"offline_time": 1546704000,
					"parent_element": 9725
				}],
				"webview": [{
						"element_id": 21931,
						"element_type": "webview",
						"title": "日常保洁",
						"subtitle": "家庭室内表面清洁、物品整理、基础除尘除垢",
						"extend": "http:\/\/m.ibantang.com\/zhekou\/search\/?q=æäººéç·&cate_id=4",
						"pic": "http://t10img.yangkeduo.com/images/2018-04-26/666f384ba3256956ba0db3cbaf521298.jpeg",
						"pic2": "",
						"time": "2小时起",
						"price": "35-40",
						"pic_width": 200,
						"pic_height": 200,
						"index": 4,
						"is_show_title": 0,
						"show_type": 1,
						"is_ad": 0,
						"tag": "0",
						"position": 0,
						"attach": "",
						"color_num": "0",
						"module_id": 101,
						"offline_time": 1836489600,
						"parent_element": 21828
					},
					{
						"element_id": 21939,
						"element_type": "webview",
						"title": "周期保洁",
						"subtitle": "定期进行家庭室内表面清洁、物品整理、基础除尘除垢",
						"extend": "http:\/\/m.ibantang.com\/zhekou\/search\/?q=æ¿éç·_å°ç½éç·&cate_id=4",
						"pic": "http://t03img.yangkeduo.com/images/2018-04-26/ed045ddb6d1f93264523807c942d6ad4.jpeg",
						"pic2": "",
						"pic_width": 200,
						"pic_height": 200,
					  	"time": "每月4次起",
						"price": "30-40",
						"index": 4,
						"is_show_title": 0,
						"show_type": 1,
						"is_ad": 0,
						"tag": "0",
						"position": 0,
						"attach": "",
						"color_num": "0",
						"module_id": 101,
						"offline_time": 1836489600,
						"parent_element": 21828
					},
					{
						"element_id": 21946,
						"element_type": "webview",
						"title": "深度保洁",
						"subtitle": "适用于三个月以上或很久未彻底清洁的房屋",
						"extend": "http:\/\/m.ibantang.com\/zhekou\/search\/?q=è¿å¨éç·&cate_id=4",
						"pic": "http://t08img.yangkeduo.com/images/2018-03-01/1ad3e18be88873e82b68c8a8a8e80133.png",
						"pic2": "",
						"pic_width": 200,
						"pic_height": 200,
					  	"time": "会员享8.5折",
						"price": "1030",
						"index": 4,
						"is_show_title": 0,
						"show_type": 1,
						"is_ad": 0,
						"tag": "0",
						"position": 0,
						"attach": "",
						"color_num": "0",
						"module_id": 101,
						"offline_time": 1836489600,
						"parent_element": 21828
					},
					{
						"element_id": 21953,
						"element_type": "webview",
						"title": "洗衣机清洗",
						"subtitle": "男鞋",
						"extend": "http:\/\/m.ibantang.com\/zhekou\/search\/?q=å¸å¸éç·&cate_id=4",
						"pic": "http://t09img.yangkeduo.com/images/2018-04-26/80cf50300d32f1c87a6748dc1c1f34c6.jpeg",
						"pic2": "",
						"pic_width": 200,
						"pic_height": 200,
						"index": 4,
						"is_show_title": 0,
						"show_type": 1,
						"is_ad": 0,
						"tag": "0",
						"position": 0,
						"attach": "",
						"color_num": "0",
						"module_id": 101,
						"offline_time": 1836489600,
						"parent_element": 21828
					},
					{
						"element_id": 21961,
						"element_type": "webview",
						"title": "油烟机清洗",
						"subtitle": "男鞋",
						"extend": "http:\/\/m.ibantang.com\/zhekou\/search\/?q=é´å­ç·_é©¬ä¸é´ç·_è±ä¼¦ç·é´_éªå°é´ç·&cate_id=4",
						"pic": "http://t09img.yangkeduo.com/images/2018-04-26/de62eded51bc0adebbf91bd3ae594cc1.jpeg",
						"pic2": "",
						"pic_width": 200,
						"pic_height": 200,
						"index": 5,
						"is_show_title": 0,
						"show_type": 1,
						"is_ad": 0,
						"tag": "0",
						"position": 0,
						"attach": "",
						"color_num": "0",
						"module_id": 101,
						"offline_time": 1836489600,
						"parent_element": 21828
					},
					{
						"element_id": 21963,
						"element_type": "webview",
						"title": "空调清洗",
						"subtitle": "男鞋",
						"extend": "http:\/\/m.ibantang.com\/zhekou\/search\/?q=ç®éç·_æ­£è£éç·&cate_id=4",
						"pic": "http://t07img.yangkeduo.com/images/2018-04-26/80b34919b15a3b3cadade885782668f3.jpeg",
						"pic2": "",
						"pic_width": 200,
						"pic_height": 200,
						"index": 6,
						"is_show_title": 0,
						"show_type": 1,
						"is_ad": 0,
						"tag": "0",
						"position": 0,
						"attach": "",
						"color_num": "0",
						"module_id": 101,
						"offline_time": 1836489600,
						"parent_element": 21828
					},
					{
						"element_id": 21966,
						"element_type": "webview",
						"title": "热水器清洗",
						"subtitle": "男鞋",
						"extend": "http:\/\/m.ibantang.com\/zhekou\/search\/?q=æéç·&cate_id=4",
						"pic": "http://t11img.yangkeduo.com/images/2018-04-26/0d4df8af6cb197cbb2a421376e1b95bb.jpeg",
						"pic2": "",
						"pic_width": 200,
						"pic_height": 200,
						"index": 7,
						"is_show_title": 0,
						"show_type": 1,
						"is_ad": 0,
						"tag": "0",
						"position": 0,
						"attach": "",
						"color_num": "0",
						"module_id": 101,
						"offline_time": 1836489600,
						"parent_element": 21828
					},
					{
						"element_id": 21967,
						"element_type": "webview",
						"title": "冰箱清洗",
						"subtitle": "男鞋",
						"extend": "http:\/\/m.ibantang.com\/zhekou\/search\/?q=æéç·&cate_id=4",
						"pic": "http://t11img.yangkeduo.com/images/2018-04-26/0d4df8af6cb197cbb2a421376e1b95bb.jpeg",
						"pic2": "",
						"pic_width": 200,
						"pic_height": 200,
						"index": 8,
						"is_show_title": 0,
						"show_type": 1,
						"is_ad": 0,
						"tag": "0",
						"position": 0,
						"attach": "",
						"color_num": "0",
						"module_id": 101,
						"offline_time": 1836489600,
						"parent_element": 21828
					},
					{
						"element_id": 2198,
						"element_type": "webview",
						"title": "饮水机清洗",
						"subtitle": "男鞋",
						"extend": "http:\/\/m.ibantang.com\/zhekou\/search\/?q=æéç·&cate_id=4",
						"pic": "http://t11img.yangkeduo.com/images/2018-04-26/0d4df8af6cb197cbb2a421376e1b95bb.jpeg",
						"pic2": "",
						"pic_width": 200,
						"pic_height": 200,
						"index": 9,
						"is_show_title": 0,
						"show_type": 1,
						"is_ad": 0,
						"tag": "0",
						"position": 0,
						"attach": "",
						"color_num": "0",
						"module_id": 101,
						"offline_time": 1836489600,
						"parent_element": 21828
					},
					{
						"element_id": 21969,
						"element_type": "webview",
						"title": "擦玻璃",
						"subtitle": "男鞋",
						"extend": "http:\/\/m.ibantang.com\/zhekou\/search\/?q=æéç·&cate_id=4",
						"pic": "http://t11img.yangkeduo.com/images/2018-04-26/0d4df8af6cb197cbb2a421376e1b95bb.jpeg",
						"pic2": "",
						"pic_width": 200,
						"pic_height": 200,
						"index": 10,
						"is_show_title": 0,
						"show_type": 1,
						"is_ad": 0,
						"tag": "0",
						"position": 0,
						"attach": "",
						"color_num": "0",
						"module_id": 101,
						"offline_time": 1836489600,
						"parent_element": 21828
					},
					{
						"element_id": 21970,
						"element_type": "webview",
						"title": "灯具清洗",
						"subtitle": "男鞋",
						"extend": "http:\/\/m.ibantang.com\/zhekou\/search\/?q=æéç·&cate_id=4",
						"pic": "http://t11img.yangkeduo.com/images/2018-04-26/0d4df8af6cb197cbb2a421376e1b95bb.jpeg",
						"pic2": "",
						"pic_width": 200,
						"pic_height": 200,
						"index": 11,
						"is_show_title": 0,
						"show_type": 1,
						"is_ad": 0,
						"tag": "0",
						"position": 0,
						"attach": "",
						"color_num": "0",
						"module_id": 101,
						"offline_time": 1836489600,
						"parent_element": 21828
					},
					{
						"element_id": 21971,
						"element_type": "webview",
						"title": "地毯清洗",
						"subtitle": "男鞋",
						"extend": "http:\/\/m.ibantang.com\/zhekou\/search\/?q=æéç·&cate_id=4",
						"pic": "http://t11img.yangkeduo.com/images/2018-04-26/0d4df8af6cb197cbb2a421376e1b95bb.jpeg",
						"pic2": "",
						"pic_width": 200,
						"pic_height": 200,
						"index": 12,
						"is_show_title": 0,
						"show_type": 1,
						"is_ad": 0,
						"tag": "0",
						"position": 0,
						"attach": "",
						"color_num": "0",
						"module_id": 101,
						"offline_time": 1836489600,
						"parent_element": 21828
					},
					{
						"element_id": 21972,
						"element_type": "webview",
						"title": "窗帘清洗",
						"subtitle": "男鞋",
						"extend": "http:\/\/m.ibantang.com\/zhekou\/search\/?q=æéç·&cate_id=4",
						"pic": "http://t11img.yangkeduo.com/images/2018-04-26/0d4df8af6cb197cbb2a421376e1b95bb.jpeg",
						"pic2": "",
						"pic_width": 200,
						"pic_height": 200,
						"index": 13,
						"is_show_title": 0,
						"show_type": 1,
						"is_ad": 0,
						"tag": "0",
						"position": 0,
						"attach": "",
						"color_num": "0",
						"module_id": 101,
						"offline_time": 1836489600,
						"parent_element": 21828
					},
					{
						"element_id": 21973,
						"element_type": "webview",
						"title": "床垫清洗",
						"subtitle": "男鞋",
						"extend": "http:\/\/m.ibantang.com\/zhekou\/search\/?q=æéç·&cate_id=4",
						"pic": "http://t11img.yangkeduo.com/images/2018-04-26/0d4df8af6cb197cbb2a421376e1b95bb.jpeg",
						"pic2": "",
						"pic_width": 200,
						"pic_height": 200,
						"index": 14,
						"is_show_title": 0,
						"show_type": 1,
						"is_ad": 0,
						"tag": "0",
						"position": 0,
						"attach": "",
						"color_num": "0",
						"module_id": 101,
						"offline_time": 1836489600,
						"parent_element": 21828
					}
				]
			}
		},
		{
			"element_id": 23271,
			"element_type": "webview",
			"title": "保姆月嫂",
			"subtitle": "0",
			"extend": "",
			"pic": "",
			"pic2": "",
			"pic_width": 0,
			"pic_height": 0,
			"index": 4,
			"is_show_title": 0,
			"show_type": 1,
			"is_ad": 0,
			"tag": "0",
			"position": 0,
			"attach": "",
			"color_num": "0",
			"module_id": 100,
			"offline_time": 2147483647,
			"parent_element": 0,
			"children": {
				"banner": [{
					"element_id": 9744,
					"element_type": "banner",
					"title": "banner",
					"subtitle": "",
					"extend": "http:\/\/m.sqkb.com\/coupon\/23027382\/",
					"pic": "http:\/\/file.17gwx.com\/sqkb\/element\/2018\/03\/12\/402425aa5fa0541daa.jpg",
					"pic2": "",
					"pic_width": 900,
					"pic_height": 288,
					"index": 5,
					"is_show_title": 0,
					"show_type": 1,
					"is_ad": 0,
					"tag": "0",
					"position": 0,
					"attach": {
						"channel_id": "222"
					},
					"color_num": "0",
					"module_id": 101,
					"offline_time": 1546704000,
					"parent_element": 9725
				}],
				"webview": [{
						"element_id": 23278,
						"element_type": "webview",
						"title": "保姆",
						"subtitle": "",
						"extend": "http:\/\/m.ibantang.com\/zhekou\/g\/494",
						"pic": "http://t07img.yangkeduo.com/images/2018-04-12/087dbfe8689cd7bb98eb01ecd999d78e.jpeg",
						"pic2": "",
						"pic_width": 200,
						"pic_height": 200,
						"index": 1,
						"is_show_title": 0,
						"show_type": 1,
						"is_ad": 0,
						"tag": "0",
						"position": 0,
						"attach": "",
						"color_num": "0",
						"module_id": 101,
						"offline_time": 2147483647,
						"parent_element": 23271
					},
					{
						"element_id": 23276,
						"element_type": "webview",
						"title": "月嫂",
						"subtitle": "",
						"extend": "http:\/\/m.ibantang.com\/zhekou\/g\/495",
						"pic": "http://t09img.yangkeduo.com/images/2018-04-12/0cf6d11479efdc94c6ed375ebcefae8d.jpeg",
						"pic2": "",
						"pic_width": 200,
						"pic_height": 200,
						"index": 2,
						"is_show_title": 0,
						"show_type": 1,
						"is_ad": 0,
						"tag": "0",
						"position": 0,
						"attach": "",
						"color_num": "0",
						"module_id": 101,
						"offline_time": 2147483647,
						"parent_element": 23271
					},
					{
						"element_id": 23284,
						"element_type": "webview",
						"title": "育儿嫂",
						"subtitle": "",
						"extend": "http:\/\/m.ibantang.com\/zhekou\/g\/440",
						"pic": "http://t07img.yangkeduo.com/images/2018-04-12/23c0549881edcafea7d3bd901b2caedd.jpeg",
						"pic2": "",
						"pic_width": 200,
						"pic_height": 200,
						"index": 3,
						"is_show_title": 0,
						"show_type": 1,
						"is_ad": 0,
						"tag": "0",
						"position": 0,
						"attach": "",
						"color_num": "0",
						"module_id": 101,
						"offline_time": 2147483647,
						"parent_element": 23271
					}
				]
			}
		},
		{
			"element_id": 21830,
			"element_type": "webview",
			"title": "搬家",
			"subtitle": "0",
			"extend": "",
			"pic": "",
			"pic2": "",
			"pic_width": 0,
			"pic_height": 0,
			"index": 5,
			"is_show_title": 0,
			"show_type": 1,
			"is_ad": 0,
			"tag": "0",
			"position": 0,
			"attach": "",
			"color_num": "0",
			"module_id": 100,
			"offline_time": 1735315200,
			"parent_element": 0,
			"children": {
				"banner": [{
					"element_id": 9744,
					"element_type": "banner",
					"title": "banner",
					"subtitle": "",
					"extend": "http:\/\/m.sqkb.com\/coupon\/23027382\/",
					"pic": "http:\/\/file.17gwx.com\/sqkb\/element\/2018\/03\/12\/402425aa5fa0541daa.jpg",
					"pic2": "",
					"pic_width": 900,
					"pic_height": 288,
					"index": 6,
					"is_show_title": 0,
					"show_type": 1,
					"is_ad": 0,
					"tag": "0",
					"position": 0,
					"attach": {
						"channel_id": "222"
					},
					"color_num": "0",
					"module_id": 101,
					"offline_time": 1546704000,
					"parent_element": 9725
				}],
				"webview": [{
						"element_id": 23046,
						"element_type": "webview",
						"title": "日式搬家",
						"subtitle": "",
						"extend": "http:\/\/m.ibantang.com\/zhekou\/g\/415",
						"pic": "http://t02img.yangkeduo.com/images/2018-04-24/7c56f4aa33866373100687a1355e7519.png",
						"pic2": "",
						"pic_width": 200,
						"pic_height": 200,
						"index": 1,
						"is_show_title": 0,
						"show_type": 1,
						"is_ad": 0,
						"tag": "0",
						"position": 0,
						"attach": "",
						"color_num": "0",
						"module_id": 101,
						"offline_time": 1838908800,
						"parent_element": 21830
					},
					{
						"element_id": 23048,
						"element_type": "webview",
						"title": "跨省搬家",
						"subtitle": "",
						"extend": "http:\/\/m.ibantang.com\/zhekou\/g\/416",
						"pic": "http://t02img.yangkeduo.com/images/2018-04-24/7c56f4aa33866373100687a1355e7519.png",
						"pic2": "",
						"pic_width": 200,
						"pic_height": 200,
						"index": 2,
						"is_show_title": 0,
						"show_type": 1,
						"is_ad": 0,
						"tag": "0",
						"position": 0,
						"attach": "",
						"color_num": "0",
						"module_id": 101,
						"offline_time": 1838908800,
						"parent_element": 21830
					},
					{
						"element_id": 23050,
						"element_type": "webview",
						"title": "普通搬家",
						"subtitle": "",
						"extend": "http:\/\/m.ibantang.com\/zhekou\/g\/417",
						"pic": "http://t02img.yangkeduo.com/images/2018-04-24/6a9722a0809eb14126f013d19ee6f868.png",
						"pic2": "",
						"pic_width": 200,
						"pic_height": 200,
						"index": 3,
						"is_show_title": 0,
						"show_type": 1,
						"is_ad": 0,
						"tag": "0",
						"position": 0,
						"attach": "",
						"color_num": "0",
						"module_id": 101,
						"offline_time": 1838908800,
						"parent_element": 21830
					}
				]
			}
		},
		{
			"element_id": 21832,
			"element_type": "webview",
			"title": "房屋维修",
			"subtitle": "0",
			"extend": "",
			"pic": "",
			"pic2": "",
			"pic_width": 0,
			"pic_height": 0,
			"index": 6,
			"is_show_title": 0,
			"show_type": 1,
			"is_ad": 0,
			"tag": "0",
			"position": 0,
			"attach": "",
			"color_num": "0",
			"module_id": 100,
			"offline_time": 1735401600,
			"parent_element": 0,
			"children": {
				"banner": [{
					"element_id": 9744,
					"element_type": "banner",
					"title": "banner",
					"subtitle": "",
					"extend": "http:\/\/m.sqkb.com\/coupon\/23027382\/",
					"pic": "http:\/\/file.17gwx.com\/sqkb\/element\/2018\/03\/12\/402425aa5fa0541daa.jpg",
					"pic2": "",
					"pic_width": 900,
					"pic_height": 288,
					"index": 7,
					"is_show_title": 0,
					"show_type": 1,
					"is_ad": 0,
					"tag": "0",
					"position": 0,
					"attach": {
						"channel_id": "222"
					},
					"color_num": "0",
					"module_id": 101,
					"offline_time": 1546704000,
					"parent_element": 9725
				}],
				"webview": [{
						"element_id": 21854,
						"element_type": "webview",
						"title": "马桶疏通",
						"subtitle": "",
						"extend": "http:\/\/m.ibantang.com\/zhekou\/g\/401",
						"pic": "http://t08img.yangkeduo.com/images/2018-04-03/55384b5db25f538f2a6c8f1e2278a89a.png",
						"pic2": "",
						"pic_width": 200,
						"pic_height": 200,
						"index": 1,
						"is_show_title": 0,
						"show_type": 1,
						"is_ad": 0,
						"tag": "0",
						"position": 0,
						"attach": "",
						"color_num": "0",
						"module_id": 101,
						"offline_time": 1836489600,
						"parent_element": 21832
					},
					{
						"element_id": 21865,
						"element_type": "webview",
						"title": "地漏疏通",
						"subtitle": "",
						"extend": "http:\/\/m.ibantang.com\/zhekou\/g\/402",
						"pic": "http://t01img.yangkeduo.com/images/2018-03-08/5ac199f6a2d101db9d8bb041b4093452.png",
						"pic2": "",
						"pic_width": 200,
						"pic_height": 200,
						"index": 2,
						"is_show_title": 0,
						"show_type": 1,
						"is_ad": 0,
						"tag": "0",
						"position": 0,
						"attach": "",
						"color_num": "0",
						"module_id": 101,
						"offline_time": 1836489600,
						"parent_element": 21832
					},
					{
						"element_id": 21874,
						"element_type": "webview",
						"title": "洗菜盆疏通",
						"subtitle": "",
						"extend": "http:\/\/m.ibantang.com\/zhekou\/search\/?q=ç¹äº§",
						"pic": "http://t10img.yangkeduo.com/images/2018-04-03/22b4c59188ba26a02db1144a22c4515e.png",
						"pic2": "",
						"pic_width": 200,
						"pic_height": 200,
						"index": 3,
						"is_show_title": 0,
						"show_type": 1,
						"is_ad": 0,
						"tag": "0",
						"position": 0,
						"attach": "",
						"color_num": "0",
						"module_id": 101,
						"offline_time": 1836489600,
						"parent_element": 21832
					},
					{
						"element_id": 21884,
						"element_type": "webview",
						"title": "洗手盆疏通",
						"subtitle": "",
						"extend": "http:\/\/m.ibantang.com\/zhekou\/g\/403",
						"pic": "http://t01img.yangkeduo.com/images/2018-03-08/186be04f9df7902e0ffa5c4bf7c5f5a8.png",
						"pic2": "",
						"pic_width": 200,
						"pic_height": 200,
						"index": 4,
						"is_show_title": 0,
						"show_type": 1,
						"is_ad": 0,
						"tag": "0",
						"position": 0,
						"attach": "",
						"color_num": "0",
						"module_id": 101,
						"offline_time": 1836489600,
						"parent_element": 21832
					},
					{
						"element_id": 21895,
						"element_type": "webview",
						"title": "浴缸疏通",
						"subtitle": "",
						"extend": "http:\/\/m.ibantang.com\/zhekou\/g\/404",
						"pic": "http://t04img.yangkeduo.com/images/2018-03-08/40e809e3cebc47f8351cd2c236acaa73.png",
						"pic2": "",
						"pic_width": 200,
						"pic_height": 200,
						"index": 5,
						"is_show_title": 0,
						"show_type": 1,
						"is_ad": 0,
						"tag": "0",
						"position": 0,
						"attach": "",
						"color_num": "0",
						"module_id": 101,
						"offline_time": 1836489600,
						"parent_element": 21832
					},
					{
						"element_id": 21903,
						"element_type": "webview",
						"title": "蹲坑疏通",
						"subtitle": "",
						"extend": "http:\/\/m.ibantang.com\/zhekou\/g\/405",
						"pic": "http://t02img.yangkeduo.com/images/2018-03-08/9d29835e6b521ea7b678e1ba3d8689cd.jpeg",
						"pic2": "",
						"pic_width": 200,
						"pic_height": 200,
						"index": 6,
						"is_show_title": 0,
						"show_type": 1,
						"is_ad": 0,
						"tag": "0",
						"position": 0,
						"attach": "",
						"color_num": "0",
						"module_id": 101,
						"offline_time": 1836489600,
						"parent_element": 21832
					},
					{
						"element_id": 21907,
						"element_type": "webview",
						"title": "小便池疏通",
						"subtitle": "",
						"extend": "http:\/\/m.ibantang.com\/zhekou\/g\/406",
						"pic": "http://t11img.yangkeduo.com/images/2018-03-08/b4c36af1e9ed3049a101cfbb829d51f7.png",
						"pic2": "",
						"pic_width": 200,
						"pic_height": 200,
						"index": 7,
						"is_show_title": 0,
						"show_type": 1,
						"is_ad": 0,
						"tag": "0",
						"position": 0,
						"attach": "",
						"color_num": "0",
						"module_id": 101,
						"offline_time": 1836489600,
						"parent_element": 21832
					},
					{
						"element_id": 23543,
						"element_type": "webview",
						"title": "门窗锁",
						"subtitle": "",
						"extend": "http:\/\/m.ibantang.com\/zhekou\/g\/516",
						"pic": "http:\/\/file.17gwx.com\/sqkb\/element\/2018\/04\/20\/617985ad989413d334.jpg",
						"pic2": "",
						"pic_width": 200,
						"pic_height": 200,
						"index": 8,
						"is_show_title": 0,
						"show_type": 1,
						"is_ad": 0,
						"tag": "0",
						"position": 0,
						"attach": "",
						"color_num": "0",
						"module_id": 101,
						"offline_time": 1839772800,
						"parent_element": 21832
					},
					{
						"element_id": 23547,
						"element_type": "webview",
						"title": "智能锁",
						"subtitle": "",
						"extend": "http:\/\/m.ibantang.com\/zhekou\/g\/517",
						"pic": "http:\/\/file.17gwx.com\/sqkb\/element\/2018\/04\/20\/535625ad98cc9c8946.jpg",
						"pic2": "",
						"pic_width": 200,
						"pic_height": 200,
						"index": 9,
						"is_show_title": 0,
						"show_type": 1,
						"is_ad": 0,
						"tag": "0",
						"position": 0,
						"attach": "",
						"color_num": "0",
						"module_id": 101,
						"offline_time": 1839772800,
						"parent_element": 21832
					}
				]
			}
		},
		{
			"element_id": 21833,
			"element_type": "webview",
			"title": "家电维修",
			"subtitle": "0",
			"extend": "",
			"pic": "",
			"pic2": "",
			"pic_width": 0,
			"pic_height": 0,
			"index": 7,
			"is_show_title": 0,
			"show_type": 1,
			"is_ad": 0,
			"tag": "0",
			"position": 0,
			"attach": "",
			"color_num": "0",
			"module_id": 100,
			"offline_time": 1735315200,
			"parent_element": 0,
			"children": {
				"banner": [{
					"element_id": 9744,
					"element_type": "banner",
					"title": "banner",
					"subtitle": "",
					"extend": "http:\/\/m.sqkb.com\/coupon\/23027382\/",
					"pic": "http:\/\/file.17gwx.com\/sqkb\/element\/2018\/03\/12\/402425aa5fa0541daa.jpg",
					"pic2": "",
					"pic_width": 900,
					"pic_height": 288,
					"index": 8,
					"is_show_title": 0,
					"show_type": 1,
					"is_ad": 0,
					"tag": "0",
					"position": 0,
					"attach": {
						"channel_id": "222"
					},
					"color_num": "0",
					"module_id": 101,
					"offline_time": 1546704000,
					"parent_element": 9725
				}],
				"webview": [{
						"element_id": 21942,
						"element_type": "webview",
						"title": "空调维修",
						"subtitle": "男内衣",
						"extend": "http:\/\/m.ibantang.com\/zhekou\/search\/?q=åè£¤ç·&cate_id=22",
						"pic": "http:\/\/file.17gwx.com\/sqkb\/element\/2018\/03\/13\/666755aa77dc8126b4.jpeg",
						"pic2": "",
						"pic_width": 200,
						"pic_height": 200,
						"index": 1,
						"is_show_title": 0,
						"show_type": 1,
						"is_ad": 0,
						"tag": "0",
						"position": 0,
						"attach": "",
						"color_num": "0",
						"module_id": 101,
						"offline_time": 1584028800,
						"parent_element": 21833
					},
					{
						"element_id": 21950,
						"element_type": "webview",
						"title": "冰箱维修",
						"subtitle": "男内衣",
						"extend": "http:\/\/m.ibantang.com\/zhekou\/search\/?q=è¢å­ç·&cate_id=22",
						"pic": "http:\/\/file.17gwx.com\/sqkb\/element\/2018\/03\/13\/665625aa77dbed99d9.jpeg",
						"pic2": "",
						"pic_width": 200,
						"pic_height": 200,
						"index": 2,
						"is_show_title": 0,
						"show_type": 1,
						"is_ad": 0,
						"tag": "0",
						"position": 0,
						"attach": "",
						"color_num": "0",
						"module_id": 101,
						"offline_time": 1584028800,
						"parent_element": 21833
					},
					{
						"element_id": 21957,
						"element_type": "webview",
						"title": "洗衣机维修",
						"subtitle": "男内衣",
						"extend": "http:\/\/m.ibantang.com\/zhekou\/search\/?q=ç¡è¡£_å®¶å±æ_ç¡è¢&cate_id=22",
						"pic": "http:\/\/file.17gwx.com\/sqkb\/element\/2018\/03\/13\/229905aa77d3d72da8.jpeg",
						"pic2": "",
						"pic_width": 200,
						"pic_height": 200,
						"index": 3,
						"is_show_title": 0,
						"show_type": 1,
						"is_ad": 0,
						"tag": "0",
						"position": 0,
						"attach": "",
						"color_num": "0",
						"module_id": 101,
						"offline_time": 1584028800,
						"parent_element": 21833
					},
					{
						"element_id": 21962,
						"element_type": "webview",
						"title": "电视维修",
						"subtitle": "男内衣",
						"extend": "http:\/\/m.ibantang.com\/zhekou\/search\/?q=ä¿æè£¤_ä¿æåè¡£_ä¿æèå¿&cate_id=22",
						"pic": "http:\/\/file.17gwx.com\/sqkb\/element\/2018\/03\/13\/307535aa77da72fc2b.jpeg",
						"pic2": "",
						"pic_width": 200,
						"pic_height": 200,
						"index": 4,
						"is_show_title": 0,
						"show_type": 1,
						"is_ad": 0,
						"tag": "0",
						"position": 0,
						"attach": "",
						"color_num": "0",
						"module_id": 101,
						"offline_time": 1584028800,
						"parent_element": 21833
					},
					{
						"element_id": 21963,
						"element_type": "webview",
						"title": "热水器维修",
						"subtitle": "男内衣",
						"extend": "http:\/\/m.ibantang.com\/zhekou\/search\/?q=ä¿æè£¤_ä¿æåè¡£_ä¿æèå¿&cate_id=22",
						"pic": "http:\/\/file.17gwx.com\/sqkb\/element\/2018\/03\/13\/307535aa77da72fc2b.jpeg",
						"pic2": "",
						"pic_width": 200,
						"pic_height": 200,
						"index": 5,
						"is_show_title": 0,
						"show_type": 1,
						"is_ad": 0,
						"tag": "0",
						"position": 0,
						"attach": "",
						"color_num": "0",
						"module_id": 101,
						"offline_time": 1584028800,
						"parent_element": 21833
					},
					{
						"element_id": 21964,
						"element_type": "webview",
						"title": "油烟机维修",
						"subtitle": "男内衣",
						"extend": "http:\/\/m.ibantang.com\/zhekou\/search\/?q=ä¿æè£¤_ä¿æåè¡£_ä¿æèå¿&cate_id=22",
						"pic": "http:\/\/file.17gwx.com\/sqkb\/element\/2018\/03\/13\/307535aa77da72fc2b.jpeg",
						"pic2": "",
						"pic_width": 200,
						"pic_height": 200,
						"index": 6,
						"is_show_title": 0,
						"show_type": 1,
						"is_ad": 0,
						"tag": "0",
						"position": 0,
						"attach": "",
						"color_num": "0",
						"module_id": 101,
						"offline_time": 1584028800,
						"parent_element": 21833
					},
					{
						"element_id": 21965,
						"element_type": "webview",
						"title": "燃气灶维修",
						"subtitle": "男内衣",
						"extend": "http:\/\/m.ibantang.com\/zhekou\/search\/?q=ä¿æè£¤_ä¿æåè¡£_ä¿æèå¿&cate_id=22",
						"pic": "http:\/\/file.17gwx.com\/sqkb\/element\/2018\/03\/13\/307535aa77da72fc2b.jpeg",
						"pic2": "",
						"pic_width": 200,
						"pic_height": 200,
						"index": 7,
						"is_show_title": 0,
						"show_type": 1,
						"is_ad": 0,
						"tag": "0",
						"position": 0,
						"attach": "",
						"color_num": "0",
						"module_id": 101,
						"offline_time": 1584028800,
						"parent_element": 21833
					},
					{
						"element_id": 21966,
						"element_type": "webview",
						"title": "净水器维修",
						"subtitle": "男内衣",
						"extend": "http:\/\/m.ibantang.com\/zhekou\/search\/?q=ä¿æè£¤_ä¿æåè¡£_ä¿æèå¿&cate_id=22",
						"pic": "http:\/\/file.17gwx.com\/sqkb\/element\/2018\/03\/13\/307535aa77da72fc2b.jpeg",
						"pic2": "",
						"pic_width": 200,
						"pic_height": 200,
						"index": 8,
						"is_show_title": 0,
						"show_type": 1,
						"is_ad": 0,
						"tag": "0",
						"position": 0,
						"attach": "",
						"color_num": "0",
						"module_id": 101,
						"offline_time": 1584028800,
						"parent_element": 21833
					},
					{
						"element_id": 21967,
						"element_type": "webview",
						"title": "饮水机维修",
						"subtitle": "男内衣",
						"extend": "http:\/\/m.ibantang.com\/zhekou\/search\/?q=ä¿æè£¤_ä¿æåè¡£_ä¿æèå¿&cate_id=22",
						"pic": "http:\/\/file.17gwx.com\/sqkb\/element\/2018\/03\/13\/307535aa77da72fc2b.jpeg",
						"pic2": "",
						"pic_width": 200,
						"pic_height": 200,
						"index": 9,
						"is_show_title": 0,
						"show_type": 1,
						"is_ad": 0,
						"tag": "0",
						"position": 0,
						"attach": "",
						"color_num": "0",
						"module_id": 101,
						"offline_time": 1584028800,
						"parent_element": 21833
					}
				]
			}
		},
		{
			"element_id": 21834,
			"element_type": "webview",
			"title": "数码维修",
			"subtitle": "0",
			"extend": "",
			"pic": "",
			"pic2": "",
			"pic_width": 0,
			"pic_height": 0,
			"index": 8,
			"is_show_title": 0,
			"show_type": 1,
			"is_ad": 0,
			"tag": "0",
			"position": 0,
			"attach": "",
			"color_num": "0",
			"module_id": 100,
			"offline_time": 1735401600,
			"parent_element": 0,
			"children": {
				"banner": [{
					"element_id": 9744,
					"element_type": "banner",
					"title": "banner",
					"subtitle": "",
					"extend": "http:\/\/m.sqkb.com\/coupon\/23027382\/",
					"pic": "http:\/\/file.17gwx.com\/sqkb\/element\/2018\/03\/12\/402425aa5fa0541daa.jpg",
					"pic2": "",
					"pic_width": 900,
					"pic_height": 288,
					"index": 9,
					"is_show_title": 0,
					"show_type": 1,
					"is_ad": 0,
					"tag": "0",
					"position": 0,
					"attach": {
						"channel_id": "222"
					},
					"color_num": "0",
					"module_id": 101,
					"offline_time": 1546704000,
					"parent_element": 9725
				}],
				"webview": [{
						"element_id": 21987,
						"element_type": "webview",
						"title": "电脑维修",
						"subtitle": "",
						"extend": "http:\/\/m.ibantang.com\/zhekou\/search\/?q=ç·å£«æ´é¢å¥¶_ç·å£«æ´é¢&cate_id=21",
						"pic": "http:\/\/file.17gwx.com\/sqkb\/element\/2018\/03\/13\/518765aa77fa54a5a5.jpeg",
						"pic2": "",
						"pic_width": 200,
						"pic_height": 200,
						"index": 1,
						"is_show_title": 0,
						"show_type": 1,
						"is_ad": 0,
						"tag": "0",
						"position": 0,
						"attach": "",
						"color_num": "0",
						"module_id": 101,
						"offline_time": 1736006400,
						"parent_element": 21834
					},
					{
						"element_id": 22006,
						"element_type": "webview",
						"title": "重装系统",
						"subtitle": "男",
						"extend": "http:\/\/m.ibantang.com\/zhekou\/search\/?q=ç·å£«ä¹³æ¶²_ç·å£«é¢é&cate_id=21",
						"pic": "http:\/\/file.17gwx.com\/sqkb\/element\/2018\/03\/13\/425845aa780b85a785.jpeg",
						"pic2": "",
						"pic_width": 200,
						"pic_height": 200,
						"index": 2,
						"is_show_title": 0,
						"show_type": 1,
						"is_ad": 0,
						"tag": "0",
						"position": 0,
						"attach": "",
						"color_num": "0",
						"module_id": 101,
						"offline_time": 1735401600,
						"parent_element": 21834
					},
					{
						"element_id": 22011,
						"element_type": "webview",
						"title": "打印机维修",
						"subtitle": "",
						"extend": "http:\/\/m.ibantang.com\/zhekou\/search\/?q=ç·å£«æ¤è¤å¥è£&cate_id=21",
						"pic": "http:\/\/file.17gwx.com\/sqkb\/element\/2018\/03\/13\/248755aa78117d391c.jpeg",
						"pic2": "",
						"pic_width": 200,
						"pic_height": 200,
						"index": 3,
						"is_show_title": 0,
						"show_type": 1,
						"is_ad": 0,
						"tag": "0",
						"position": 0,
						"attach": "",
						"color_num": "0",
						"module_id": 101,
						"offline_time": 1735315200,
						"parent_element": 21834
					},
					{
						"element_id": 22014,
						"element_type": "webview",
						"title": "电脑加速",
						"subtitle": "",
						"extend": "http:\/\/m.ibantang.com\/zhekou\/search\/?q=ç·å£«é¢è&cate_id=21",
						"pic": "http:\/\/file.17gwx.com\/sqkb\/element\/2018\/03\/13\/621245aa7814d04cd7.jpeg",
						"pic2": "",
						"pic_width": 200,
						"pic_height": 200,
						"index": 4,
						"is_show_title": 0,
						"show_type": 1,
						"is_ad": 0,
						"tag": "0",
						"position": 0,
						"attach": "",
						"color_num": "0",
						"module_id": 101,
						"offline_time": 1735401600,
						"parent_element": 21834
					},
					{
						"element_id": 22026,
						"element_type": "webview",
						"title": "电脑除尘",
						"subtitle": "",
						"extend": "http:\/\/m.ibantang.com\/zhekou\/search\/?q=ç·å£«å½©å¦_ç·å£«çç¬_ç·å£«çç²_ç·å£«æçè_ç·å£«ç²åºæ¶²_ç·å£«BBé_ç·å£«ç¼çº¿ç¬_ç·å£«ç¼å½±_ç·å£«å£çº¢&cate_id=21",
						"pic": "http:\/\/file.17gwx.com\/sqkb\/element\/2018\/03\/13\/396095aa781c1e11b4.jpeg",
						"pic2": "",
						"pic_width": 200,
						"pic_height": 200,
						"index": 5,
						"is_show_title": 0,
						"show_type": 1,
						"is_ad": 0,
						"tag": "0",
						"position": 0,
						"attach": "",
						"color_num": "0",
						"module_id": 101,
						"offline_time": 1735315200,
						"parent_element": 21834
					},
					{
						"element_id": 22029,
						"element_type": "webview",
						"title": "手机维修",
						"subtitle": "",
						"extend": "http:\/\/m.ibantang.com\/zhekou\/search\/?q=åé¡»å&cate_id=21",
						"pic": "http:\/\/file.17gwx.com\/sqkb\/element\/2018\/03\/13\/835465aa781f3d2d6d.jpeg",
						"pic2": "",
						"pic_width": 200,
						"pic_height": 200,
						"index": 6,
						"is_show_title": 0,
						"show_type": 1,
						"is_ad": 0,
						"tag": "0",
						"position": 0,
						"attach": "",
						"color_num": "0",
						"module_id": 101,
						"offline_time": 1735401600,
						"parent_element": 21834
					},
					{
						"element_id": 22032,
						"element_type": "webview",
						"title": "网络修复",
						"subtitle": "",
						"extend": "http:\/\/m.ibantang.com\/zhekou\/search\/?q=ç·å£«åè¡_ç·å£«å«å±æ°´_ç·å£«åè¶_ç·å£«å®åå·é¾_ç·å£«å®ååæ³¥&cate_id=21",
						"pic": "http:\/\/file.17gwx.com\/sqkb\/element\/2018\/03\/13\/822945aa78226d2380.jpeg",
						"pic2": "",
						"pic_width": 200,
						"pic_height": 200,
						"index": 7,
						"is_show_title": 0,
						"show_type": 1,
						"is_ad": 0,
						"tag": "0",
						"position": 0,
						"attach": "",
						"color_num": "0",
						"module_id": 101,
						"offline_time": 1735401600,
						"parent_element": 21834
					}
				]
			}
		},
		{
			"element_id": 21835,
			"element_type": "webview",
			"title": "上门安装",
			"subtitle": "0",
			"extend": "",
			"pic": "",
			"pic2": "",
			"pic_width": 0,
			"pic_height": 0,
			"index": 9,
			"is_show_title": 0,
			"show_type": 1,
			"is_ad": 0,
			"tag": "0",
			"position": 0,
			"attach": "",
			"color_num": "0",
			"module_id": 100,
			"offline_time": 1735401600,
			"parent_element": 0,
			"children": {
				"banner": [{
					"element_id": 9744,
					"element_type": "banner",
					"title": "banner",
					"subtitle": "",
					"extend": "http:\/\/m.sqkb.com\/coupon\/23027382\/",
					"pic": "http:\/\/file.17gwx.com\/sqkb\/element\/2018\/03\/12\/402425aa5fa0541daa.jpg",
					"pic2": "",
					"pic_width": 900,
					"pic_height": 288,
					"index": 10,
					"is_show_title": 0,
					"show_type": 1,
					"is_ad": 0,
					"tag": "0",
					"position": 0,
					"attach": {
						"channel_id": "222"
					},
					"color_num": "0",
					"module_id": 101,
					"offline_time": 1546704000,
					"parent_element": 9725
				}],
				"webview": [{
						"element_id": 21959,
						"element_type": "webview",
						"title": "水管安装",
						"subtitle": "数码男",
						"extend": "http:\/\/m.sqkb.com\/subject\/1488?use_wk=1",
						"pic": "http:\/\/file.17gwx.com\/sqkb\/element\/2018\/03\/29\/836015abc993568803.jpeg",
						"pic2": "",
						"pic_width": 200,
						"pic_height": 200,
						"index": 1,
						"is_show_title": 0,
						"show_type": 1,
						"is_ad": 0,
						"tag": "0",
						"position": 0,
						"attach": "",
						"color_num": "0",
						"module_id": 101,
						"offline_time": 1709222400,
						"parent_element": 21835
					},
					{
						"element_id": 21968,
						"element_type": "webview",
						"title": "阀门安装",
						"subtitle": "男",
						"extend": "http:\/\/m.ibantang.com\/zhekou\/search\/?q=é®ç_é¼ æ _é®é¼ å¥è£_å¤´æ´å¼è³æº_è·¯ç±å¨_é¼ æ å«_ä¸»æº_æ£ç­å¨_ä¸»æº&cate_id=9",
						"pic": "http:\/\/file.17gwx.com\/sqkb\/element\/2018\/03\/13\/546675aa77e4d30757.jpeg",
						"pic2": "",
						"pic_width": 200,
						"pic_height": 200,
						"index": 2,
						"is_show_title": 0,
						"show_type": 1,
						"is_ad": 0,
						"tag": "0",
						"position": 0,
						"attach": "",
						"color_num": "0",
						"module_id": 101,
						"offline_time": 1709222400,
						"parent_element": 21835
					},
					{
						"element_id": 21978,
						"element_type": "webview",
						"title": "插座安装",
						"subtitle": "",
						"extend": "http:\/\/m.ibantang.com\/zhekou\/search\/?q=çµè¯æè¡¨_æºè½æç¯_èäººææº_èæé_ææº_VRç¼é_æ¸¸æææ&cate_id=9",
						"pic": "http:\/\/file.17gwx.com\/sqkb\/element\/2018\/03\/13\/888015aa77f199d809.jpeg",
						"pic2": "",
						"pic_width": 200,
						"pic_height": 200,
						"index": 3,
						"is_show_title": 0,
						"show_type": 1,
						"is_ad": 0,
						"tag": "0",
						"position": 0,
						"attach": "",
						"color_num": "0",
						"module_id": 101,
						"offline_time": 1709222400,
						"parent_element": 21835
					},
					{
						"element_id": 21986,
						"element_type": "webview",
						"title": "电视安装",
						"subtitle": "",
						"extend": "http:\/\/m.ibantang.com\/zhekou\/g\/470\/",
						"pic": "http:\/\/file.17gwx.com\/sqkb\/element\/2018\/03\/27\/379275ab9edc7aa6d7.jpeg",
						"pic2": "",
						"pic_width": 200,
						"pic_height": 200,
						"index": 4,
						"is_show_title": 0,
						"show_type": 1,
						"is_ad": 0,
						"tag": "0",
						"position": 0,
						"attach": "",
						"color_num": "0",
						"module_id": 101,
						"offline_time": 1709222400,
						"parent_element": 21835
					},
					{
						"element_id": 21998,
						"element_type": "webview",
						"title": "空调安装",
						"subtitle": "男",
						"extend": "http:\/\/m.ibantang.com\/zhekou\/g\/455\/",
						"pic": "http:\/\/file.17gwx.com\/sqkb\/element\/2018\/03\/13\/970935aa7804fc474c.jpg",
						"pic2": "",
						"pic_width": 200,
						"pic_height": 200,
						"index": 5,
						"is_show_title": 0,
						"show_type": 1,
						"is_ad": 0,
						"tag": "0",
						"position": 0,
						"attach": "",
						"color_num": "0",
						"module_id": 101,
						"offline_time": 1709222400,
						"parent_element": 21835
					},
					{
						"element_id": 22019,
						"element_type": "webview",
						"title": "热水器安装",
						"subtitle": "",
						"extend": "http:\/\/m.ibantang.com\/zhekou\/search\/?q=ææºè&cate_id=9",
						"pic": "http:\/\/file.17gwx.com\/sqkb\/element\/2018\/03\/13\/156235aa78152a3448.",
						"pic2": "",
						"pic_width": 200,
						"pic_height": 200,
						"index": 6,
						"is_show_title": 0,
						"show_type": 1,
						"is_ad": 0,
						"tag": "0",
						"position": 0,
						"attach": "",
						"color_num": "0",
						"module_id": 101,
						"offline_time": 1706716800,
						"parent_element": 21835
					},
					{
						"element_id": 22034,
						"element_type": "webview",
						"title": "马桶安装",
						"subtitle": "",
						"extend": "http:\/\/m.ibantang.com\/zhekou\/search\/?q=æ°æ®çº¿&cate_id=9",
						"pic": "http:\/\/file.17gwx.com\/sqkb\/element\/2018\/03\/13\/495975aa7824067a24.",
						"pic2": "",
						"pic_width": 200,
						"pic_height": 200,
						"index": 7,
						"is_show_title": 0,
						"show_type": 1,
						"is_ad": 0,
						"tag": "0",
						"position": 0,
						"attach": "",
						"color_num": "0",
						"module_id": 101,
						"offline_time": 1722441600,
						"parent_element": 21835
					},
					{
						"element_id": 22049,
						"element_type": "webview",
						"title": "地漏安装",
						"subtitle": "",
						"extend": "http:\/\/m.ibantang.com\/zhekou\/search\/?q=éº¦åé£&cate_id=9",
						"pic": "http:\/\/file.17gwx.com\/sqkb\/element\/2018\/03\/13\/875265aa783be29ef7.",
						"pic2": "",
						"pic_width": 200,
						"pic_height": 200,
						"index": 8,
						"is_show_title": 0,
						"show_type": 1,
						"is_ad": 0,
						"tag": "0",
						"position": 0,
						"attach": "",
						"color_num": "0",
						"module_id": 101,
						"offline_time": 1709222400,
						"parent_element": 21835
					},
					{
						"element_id": 22053,
						"element_type": "webview",
						"title": "燃气灶安装",
						"subtitle": "",
						"extend": "http:\/\/m.ibantang.com\/zhekou\/search\/?q=èªææ_è¡¥åç¯_éå¤´_èªæç¥å¨&cate_id=9",
						"pic": "http:\/\/file.17gwx.com\/sqkb\/element\/2018\/03\/13\/528815aa784c1cc24b.jpg",
						"pic2": "",
						"pic_width": 200,
						"pic_height": 200,
						"index": 9,
						"is_show_title": 0,
						"show_type": 1,
						"is_ad": 0,
						"tag": "0",
						"position": 0,
						"attach": "",
						"color_num": "0",
						"module_id": 101,
						"offline_time": 1709222400,
						"parent_element": 21835
					},
					{
						"element_id": 22056,
						"element_type": "webview",
						"title": "油烟机安装",
						"subtitle": "",
						"extend": "http:\/\/m.ibantang.com\/zhekou\/search\/?q=é³å_èçé³å_è¿·ä½ é³å_é³ç®±&cate_id=9",
						"pic": "http:\/\/file.17gwx.com\/sqkb\/element\/2018\/03\/13\/823865aa7854db4a55.jpeg",
						"pic2": "",
						"pic_width": 200,
						"pic_height": 200,
						"index": 10,
						"is_show_title": 0,
						"show_type": 1,
						"is_ad": 0,
						"tag": "0",
						"position": 0,
						"attach": "",
						"color_num": "0",
						"module_id": 101,
						"offline_time": 1709222400,
						"parent_element": 21835
					},
					{
						"element_id": 22058,
						"element_type": "webview",
						"title": "洗手盆安装",
						"subtitle": "",
						"extend": "http:\/\/m.ibantang.com\/zhekou\/search\/?q=è³æº",
						"pic": "http:\/\/file.17gwx.com\/sqkb\/element\/2018\/03\/13\/645075aa785b258791.jpeg",
						"pic2": "",
						"pic_width": 200,
						"pic_height": 200,
						"index": 11,
						"is_show_title": 0,
						"show_type": 1,
						"is_ad": 0,
						"tag": "0",
						"position": 0,
						"attach": "",
						"color_num": "0",
						"module_id": 101,
						"offline_time": 1709222400,
						"parent_element": 21835
					}
				]
			}
		},
		{
			"element_id": 21836,
			"element_type": "webview",
			"title": "健康",
			"subtitle": "0",
			"extend": "",
			"pic": "",
			"pic2": "",
			"pic_width": 0,
			"pic_height": 0,
			"index": 10,
			"is_show_title": 0,
			"show_type": 1,
			"is_ad": 0,
			"tag": "0",
			"position": 0,
			"attach": "",
			"color_num": "0",
			"module_id": 100,
			"offline_time": 1735401600,
			"parent_element": 0,
			"children": {
				"banner": [{
					"element_id": 9744,
					"element_type": "banner",
					"title": "banner",
					"subtitle": "",
					"extend": "http:\/\/m.sqkb.com\/coupon\/23027382\/",
					"pic": "http:\/\/file.17gwx.com\/sqkb\/element\/2018\/03\/12\/402425aa5fa0541daa.jpg",
					"pic2": "",
					"pic_width": 900,
					"pic_height": 288,
					"index": 11,
					"is_show_title": 0,
					"show_type": 1,
					"is_ad": 0,
					"tag": "0",
					"position": 0,
					"attach": {
						"channel_id": "222"
					},
					"color_num": "0",
					"module_id": 101,
					"offline_time": 1546704000,
					"parent_element": 9725
				}],
				"webview": [{
						"element_id": 22010,
						"element_type": "webview",
						"title": "按摩理疗",
						"subtitle": "男",
						"extend": "http:\/\/m.ibantang.com\/zhekou\/search\/?q=æè¡¨&cate_id=23",
						"pic": "http:\/\/file.17gwx.com\/sqkb\/element\/2018\/03\/13\/797615aa781110072e.jpg",
						"pic2": "",
						"pic_width": 200,
						"pic_height": 200,
						"index": 1,
						"is_show_title": 0,
						"show_type": 1,
						"is_ad": 0,
						"tag": "0",
						"position": 0,
						"attach": "",
						"color_num": "0",
						"module_id": 101,
						"offline_time": 2147483647,
						"parent_element": 21836
					},
					{
						"element_id": 22018,
						"element_type": "webview",
						"title": "小儿推拿",
						"subtitle": "男",
						"extend": "m.ibantang.com\/zhekou\/g\/382",
						"pic": "http:\/\/file.17gwx.com\/sqkb\/element\/2018\/03\/13\/378055aa7814860497.jpg",
						"pic2": "",
						"pic_width": 200,
						"pic_height": 200,
						"index": 2,
						"is_show_title": 0,
						"show_type": 1,
						"is_ad": 0,
						"tag": "0",
						"position": 0,
						"attach": "",
						"color_num": "0",
						"module_id": 101,
						"offline_time": 2147483647,
						"parent_element": 21836
					},
					{
						"element_id": 22025,
						"element_type": "webview",
						"title": "局部理疗",
						"subtitle": "男",
						"extend": "http:\/\/m.ibantang.com\/zhekou\/search\/?q=è°å¸¦ç·&cate_id=23",
						"pic": "http:\/\/file.17gwx.com\/sqkb\/element\/2018\/03\/13\/798975aa781af84846.jpg",
						"pic2": "",
						"pic_width": 200,
						"pic_height": 200,
						"index": 4,
						"is_show_title": 0,
						"show_type": 1,
						"is_ad": 0,
						"tag": "0",
						"position": 0,
						"attach": "",
						"color_num": "0",
						"module_id": 101,
						"offline_time": 2147483647,
						"parent_element": 21836
					},
					{
						"element_id": 22028,
						"element_type": "webview",
						"title": "产妇护理",
						"subtitle": "男",
						"extend": "http:\/\/m.ibantang.com\/zhekou\/search\/?q=å¸½å­&cate_id=23",
						"pic": "http:\/\/file.17gwx.com\/sqkb\/element\/2018\/03\/13\/539065aa781ec37af8.jpg",
						"pic2": "",
						"pic_width": 200,
						"pic_height": 200,
						"index": 5,
						"is_show_title": 0,
						"show_type": 1,
						"is_ad": 0,
						"tag": "0",
						"position": 0,
						"attach": "",
						"color_num": "0",
						"module_id": 101,
						"offline_time": 2147483647,
						"parent_element": 21836
					},
					{
						"element_id": 22035,
						"element_type": "webview",
						"title": "老年体检",
						"subtitle": "男",
						"extend": "m.ibantang.com\/zhekou\/g\/381",
						"pic": "http:\/\/file.17gwx.com\/sqkb\/element\/2018\/03\/13\/955395aa782578863d.jpg",
						"pic2": "",
						"pic_width": 200,
						"pic_height": 200,
						"index": 6,
						"is_show_title": 0,
						"show_type": 1,
						"is_ad": 0,
						"tag": "0",
						"position": 0,
						"attach": "",
						"color_num": "0",
						"module_id": 101,
						"offline_time": 2147483647,
						"parent_element": 21836
					},
					{
						"element_id": 22037,
						"element_type": "webview",
						"title": "就医陪诊",
						"subtitle": "",
						"extend": "m.ibantang.com\/zhekou\/g\/380",
						"pic": "http:\/\/file.17gwx.com\/sqkb\/element\/2018\/03\/13\/947065aa7829c63234.jpg",
						"pic2": "",
						"pic_width": 200,
						"pic_height": 200,
						"index": 8,
						"is_show_title": 0,
						"show_type": 1,
						"is_ad": 0,
						"tag": "0",
						"position": 0,
						"attach": "",
						"color_num": "0",
						"module_id": 101,
						"offline_time": 2147483647,
						"parent_element": 21836
					},
					{
						"element_id": 22038,
						"element_type": "webview",
						"title": "医护上门",
						"subtitle": "",
						"extend": "m.ibantang.com\/zhekou\/g\/380",
						"pic": "http:\/\/file.17gwx.com\/sqkb\/element\/2018\/03\/13\/947065aa7829c63234.jpg",
						"pic2": "",
						"pic_width": 200,
						"pic_height": 200,
						"index": 9,
						"is_show_title": 0,
						"show_type": 1,
						"is_ad": 0,
						"tag": "0",
						"position": 0,
						"attach": "",
						"color_num": "0",
						"module_id": 101,
						"offline_time": 2147483647,
						"parent_element": 21836
					}
				]
			}
		},
		{
			"element_id": 21837,
			"element_type": "webview",
			"title": "鲜花美食",
			"subtitle": "0",
			"extend": "",
			"pic": "",
			"pic2": "",
			"pic_width": 0,
			"pic_height": 0,
			"index": 11,
			"is_show_title": 0,
			"show_type": 1,
			"is_ad": 0,
			"tag": "0",
			"position": 0,
			"attach": "",
			"color_num": "0",
			"module_id": 100,
			"offline_time": 1735315200,
			"parent_element": 0,
			"children": {
				"banner": [{
					"element_id": 9744,
					"element_type": "banner",
					"title": "banner",
					"subtitle": "",
					"extend": "http:\/\/m.sqkb.com\/coupon\/23027382\/",
					"pic": "http:\/\/file.17gwx.com\/sqkb\/element\/2018\/03\/12\/402425aa5fa0541daa.jpg",
					"pic2": "",
					"pic_width": 900,
					"pic_height": 288,
					"index": 1,
					"is_show_title": 0,
					"show_type": 1,
					"is_ad": 0,
					"tag": "0",
					"position": 0,
					"attach": {
						"channel_id": "222"
					},
					"color_num": "0",
					"module_id": 101,
					"offline_time": 1546704000,
					"parent_element": 9725
				}],
				"webview": [{
						"element_id": 22066,
						"element_type": "webview",
						"title": "精品玫瑰",
						"subtitle": "",
						"extend": "http:\/\/m.sqkb.com\/coupon\/operationRankDetail\/1493",
						"pic": "http:\/\/file.17gwx.com\/sqkb\/element\/2018\/03\/13\/671315aa786efc29e1.jpeg",
						"pic2": "",
						"pic_width": 200,
						"pic_height": 200,
						"index": 1,
						"is_show_title": 0,
						"show_type": 1,
						"is_ad": 0,
						"tag": "0",
						"position": 0,
						"attach": "",
						"color_num": "0",
						"module_id": 101,
						"offline_time": 1709222400,
						"parent_element": 21837
					},
					{
						"element_id": 22068,
						"element_type": "webview",
						"title": "精品百合",
						"subtitle": "",
						"extend": "http:\/\/m.ibantang.com\/zhekou\/g\/293\/",
						"pic": "http:\/\/file.17gwx.com\/sqkb\/element\/2018\/03\/13\/311125aa787ad5d925.jpg",
						"pic2": "",
						"pic_width": 200,
						"pic_height": 200,
						"index": 2,
						"is_show_title": 0,
						"show_type": 1,
						"is_ad": 0,
						"tag": "0",
						"position": 0,
						"attach": "",
						"color_num": "0",
						"module_id": 101,
						"offline_time": 1709222400,
						"parent_element": 21837
					},
					{
						"element_id": 22070,
						"element_type": "webview",
						"title": "健康餐饮",
						"subtitle": "",
						"extend": "http:\/\/m.ibantang.com\/zhekou\/g\/290\/",
						"pic": "http:\/\/file.17gwx.com\/sqkb\/element\/2018\/03\/13\/589345aa7887f7e70f.jpg",
						"pic2": "",
						"pic_width": 200,
						"pic_height": 200,
						"index": 3,
						"is_show_title": 0,
						"show_type": 1,
						"is_ad": 0,
						"tag": "0",
						"position": 0,
						"attach": "",
						"color_num": "0",
						"module_id": 101,
						"offline_time": 1709222400,
						"parent_element": 21837
					},
					{
						"element_id": 22078,
						"element_type": "webview",
						"title": "养生餐饮",
						"subtitle": "",
						"extend": "http:\/\/m.ibantang.com\/zhekou\/g\/298\/",
						"pic": "http:\/\/file.17gwx.com\/sqkb\/element\/2018\/03\/13\/605575aa78923b00ff.jpeg",
						"pic2": "",
						"pic_width": 200,
						"pic_height": 200,
						"index": 4,
						"is_show_title": 0,
						"show_type": 1,
						"is_ad": 0,
						"tag": "0",
						"position": 0,
						"attach": "",
						"color_num": "0",
						"module_id": 101,
						"offline_time": 1709222400,
						"parent_element": 21837
					},
					{
						"element_id": 22085,
						"element_type": "webview",
						"title": "特殊餐饮",
						"subtitle": "",
						"extend": "http:\/\/m.ibantang.com\/zhekou\/g\/456\/",
						"pic": "http:\/\/file.17gwx.com\/sqkb\/element\/2018\/03\/13\/554735aa78a1915e10.",
						"pic2": "",
						"pic_width": 200,
						"pic_height": 200,
						"index": 5,
						"is_show_title": 0,
						"show_type": 1,
						"is_ad": 0,
						"tag": "0",
						"position": 0,
						"attach": "",
						"color_num": "0",
						"module_id": 101,
						"offline_time": 1709222400,
						"parent_element": 21837
					},
					{
						"element_id": 22089,
						"element_type": "webview",
						"title": "家常餐饮",
						"subtitle": "",
						"extend": "http:\/\/m.ibantang.com\/zhekou\/search\/?q=æç«_çµç¨æ&cata_id=10",
						"pic": "http:\/\/file.17gwx.com\/sqkb\/element\/2018\/03\/13\/497285aa78ab8d3748.",
						"pic2": "",
						"pic_width": 200,
						"pic_height": 200,
						"index": 6,
						"is_show_title": 0,
						"show_type": 1,
						"is_ad": 0,
						"tag": "0",
						"position": 0,
						"attach": "",
						"color_num": "0",
						"module_id": 101,
						"offline_time": 1709222400,
						"parent_element": 21837
					}
				]
			}
		},
		{
			"element_id": 21838,
			"element_type": "webview",
			"title": "家庭护洗",
			"subtitle": "0",
			"extend": "",
			"pic": "",
			"pic2": "",
			"pic_width": 0,
			"pic_height": 0,
			"index": 12,
			"is_show_title": 0,
			"show_type": 1,
			"is_ad": 0,
			"tag": "0",
			"position": 0,
			"attach": "",
			"color_num": "0",
			"module_id": 100,
			"offline_time": 1735315200,
			"parent_element": 0,
			"children": {
				"banner": [{
					"element_id": 9744,
					"element_type": "banner",
					"title": "banner",
					"subtitle": "",
					"extend": "http:\/\/m.sqkb.com\/coupon\/23027382\/",
					"pic": "http:\/\/file.17gwx.com\/sqkb\/element\/2018\/03\/12\/402425aa5fa0541daa.jpg",
					"pic2": "",
					"pic_width": 900,
					"pic_height": 288,
					"index": 2,
					"is_show_title": 0,
					"show_type": 1,
					"is_ad": 0,
					"tag": "0",
					"position": 0,
					"attach": {
						"channel_id": "222"
					},
					"color_num": "0",
					"module_id": 101,
					"offline_time": 1546704000,
					"parent_element": 9725
				}],
				"webview": [{
						"element_id": 21866,
						"element_type": "webview",
						"title": "皮鞋清洗",
						"subtitle": "",
						"extend": "http:\/\/m.sqkb.com\/coupon\/operationRankDetail\/468?use_wk=1",
						"pic": "http:\/\/file.17gwx.com\/sqkb\/element\/2018\/03\/13\/150635aa778fe6baa7.jpeg",
						"pic2": "",
						"pic_width": 200,
						"pic_height": 200,
						"index": 1,
						"is_show_title": 0,
						"show_type": 1,
						"is_ad": 0,
						"tag": "0",
						"position": 0,
						"attach": "",
						"color_num": "0",
						"module_id": 101,
						"offline_time": 1735401600,
						"parent_element": 21838
					},
					{
						"element_id": 21859,
						"element_type": "webview",
						"title": "靴子清洗",
						"subtitle": "",
						"extend": "m.ibantang.com\/zhekou\/g\/336\/",
						"pic": "http:\/\/file.17gwx.com\/sqkb\/element\/2018\/03\/13\/276675aa77875bf47c.jpg",
						"pic2": "",
						"pic_width": 200,
						"pic_height": 200,
						"index": 2,
						"is_show_title": 0,
						"show_type": 1,
						"is_ad": 0,
						"tag": "0",
						"position": 0,
						"attach": "",
						"color_num": "0",
						"module_id": 101,
						"offline_time": 1735315200,
						"parent_element": 21838
					},
					{
						"element_id": 21909,
						"element_type": "webview",
						"title": "上衣清洗",
						"subtitle": "",
						"extend": "m.ibantang.com\/zhekou\/g\/337\/",
						"pic": "http:\/\/file.17gwx.com\/sqkb\/element\/2018\/03\/13\/802295aa77b10e2464.jpeg",
						"pic2": "",
						"pic_width": 200,
						"pic_height": 200,
						"index": 3,
						"is_show_title": 0,
						"show_type": 1,
						"is_ad": 0,
						"tag": "0",
						"position": 0,
						"attach": "",
						"color_num": "0",
						"module_id": 101,
						"offline_time": 1703865600,
						"parent_element": 21838
					},
					{
						"element_id": 21917,
						"element_type": "webview",
						"title": "羽绒服清洗",
						"subtitle": "",
						"extend": "m.ibantang.com\/zhekou\/g\/338\/",
						"pic": "http:\/\/file.17gwx.com\/sqkb\/element\/2018\/03\/13\/115655aa77b524eba7.jpg",
						"pic2": "",
						"pic_width": 200,
						"pic_height": 200,
						"index": 4,
						"is_show_title": 0,
						"show_type": 1,
						"is_ad": 0,
						"tag": "0",
						"position": 0,
						"attach": "",
						"color_num": "0",
						"module_id": 101,
						"offline_time": 1735401600,
						"parent_element": 21838
					},
					{
						"element_id": 21922,
						"element_type": "webview",
						"title": "裤装清洗",
						"subtitle": "",
						"extend": "m.ibantang.com\/zhekou\/g\/339\/",
						"pic": "http:\/\/file.17gwx.com\/sqkb\/element\/2018\/03\/13\/470085aa77b8457a13.jpeg",
						"pic2": "",
						"pic_width": 200,
						"pic_height": 200,
						"index": 5,
						"is_show_title": 0,
						"show_type": 1,
						"is_ad": 0,
						"tag": "0",
						"position": 0,
						"attach": "",
						"color_num": "0",
						"module_id": 101,
						"offline_time": 1735315200,
						"parent_element": 21838
					}
				]
			}
		},
		{
			"element_id": 21839,
			"element_type": "webview",
			"title": "便民服务",
			"subtitle": "0",
			"extend": "",
			"pic": "",
			"pic2": "",
			"pic_width": 0,
			"pic_height": 0,
			"index": 13,
			"is_show_title": 0,
			"show_type": 1,
			"is_ad": 0,
			"tag": "0",
			"position": 0,
			"attach": "",
			"color_num": "0",
			"module_id": 100,
			"offline_time": 1735401600,
			"parent_element": 0,
			"children": {
				"banner": [{
					"element_id": 9744,
					"element_type": "banner",
					"title": "banner",
					"subtitle": "",
					"extend": "http:\/\/m.sqkb.com\/coupon\/23027382\/",
					"pic": "http:\/\/file.17gwx.com\/sqkb\/element\/2018\/03\/12\/402425aa5fa0541daa.jpg",
					"pic2": "",
					"pic_width": 900,
					"pic_height": 288,
					"index": 3,
					"is_show_title": 0,
					"show_type": 1,
					"is_ad": 0,
					"tag": "0",
					"position": 0,
					"attach": {
						"channel_id": "222"
					},
					"color_num": "0",
					"module_id": 101,
					"offline_time": 1546704000,
					"parent_element": 9725
				}],
				"webview": [{
						"element_id": 21935,
						"element_type": "webview",
						"title": "代排队",
						"subtitle": "",
						"extend": "http:\/\/m.ibantang.com\/zhekou\/g\/329",
						"pic": "http:\/\/file.17gwx.com\/sqkb\/element\/2018\/04\/10\/920055acc351fd83f8.jpg",
						"pic2": "",
						"pic_width": 200,
						"pic_height": 200,
						"index": 1,
						"is_show_title": 0,
						"show_type": 1,
						"is_ad": 0,
						"tag": "0",
						"position": 0,
						"attach": "",
						"color_num": "0",
						"module_id": 101,
						"offline_time": 2147483647,
						"parent_element": 21839
					},
					{
						"element_id": 21944,
						"element_type": "webview",
						"title": "搬重物",
						"subtitle": "",
						"extend": "http:\/\/m.ibantang.com\/zhekou\/g\/330",
						"pic": "http:\/\/file.17gwx.com\/sqkb\/element\/2018\/04\/10\/117155acc3586c72fb.jpg",
						"pic2": "",
						"pic_width": 200,
						"pic_height": 200,
						"index": 2,
						"is_show_title": 0,
						"show_type": 1,
						"is_ad": 0,
						"tag": "0",
						"position": 0,
						"attach": "",
						"color_num": "0",
						"module_id": 101,
						"offline_time": 2147483647,
						"parent_element": 21839
					},
					{
						"element_id": 21955,
						"element_type": "webview",
						"title": "代购买",
						"subtitle": "",
						"extend": "http:\/\/m.ibantang.com\/zhekou\/g\/331",
						"pic": "http:\/\/file.17gwx.com\/sqkb\/element\/2018\/04\/10\/716385acc35d88c528.jpg",
						"pic2": "",
						"pic_width": 200,
						"pic_height": 200,
						"index": 3,
						"is_show_title": 0,
						"show_type": 1,
						"is_ad": 0,
						"tag": "0",
						"position": 0,
						"attach": "",
						"color_num": "0",
						"module_id": 101,
						"offline_time": 2147483647,
						"parent_element": 21839
					},
					{
						"element_id": 21958,
						"element_type": "webview",
						"title": "宠物服务",
						"subtitle": "",
						"extend": "http:\/\/m.ibantang.com\/zhekou\/g\/332",
						"pic": "http:\/\/file.17gwx.com\/sqkb\/element\/2018\/04\/10\/495925acc3605540cf.jpg",
						"pic2": "",
						"pic_width": 200,
						"pic_height": 200,
						"index": 4,
						"is_show_title": 0,
						"show_type": 1,
						"is_ad": 0,
						"tag": "0",
						"position": 0,
						"attach": "",
						"color_num": "0",
						"module_id": 101,
						"offline_time": 2147483647,
						"parent_element": 21839
					},
					{
						"element_id": 21970,
						"element_type": "webview",
						"title": "万能代办",
						"subtitle": "",
						"extend": "http:\/\/m.ibantang.com\/zhekou\/search\/?q=åºå«_å¸èºåº_ç®èºåº_ææ_æ¢³å¦å°_å­æ¯åº_å¿ç«¥åº_å®æ¨åº_è¡£æ_åºå¤´æ&cate_id=26",
						"pic": "http:\/\/file.17gwx.com\/sqkb\/element\/2018\/03\/13\/954015aa77e8096048.jpeg",
						"pic2": "",
						"pic_width": 200,
						"pic_height": 200,
						"index": 5,
						"is_show_title": 0,
						"show_type": 1,
						"is_ad": 0,
						"tag": "0",
						"position": 0,
						"attach": "",
						"color_num": "0",
						"module_id": 101,
						"offline_time": 2147483647,
						"parent_element": 21839
					}
				]
			}
		}
	]
}